finance/__init__.py
finance/investment.py
finance/main.py
finance/returns.py
finance/risk.py
investments/__init__.py
investments/calculator.py
intro_python_feb26_financetools_milin-0.1.0.dist-info/METADATA
intro_python_feb26_financetools_milin-0.1.0.dist-info/WHEEL
intro_python_feb26_financetools_milin-0.1.0.dist-info/top_level.txt
intro_python_feb26_financetools_milin-0.1.0.dist-info/RECORD
