Metadata-Version: 2.2
Name: intro-python-feb26_financetools_milin
Version: 0.1.0
Summary: ,
Author: Milin Dalal
License: MIT
Requires-Dist: numpy
Requires-Dist: pandas
Dynamic: author
Dynamic: license
Dynamic: requires-dist
Dynamic: summary
